Workbook

Sheet Sheet2
B1: Cumulative | C1: Incremental
A2: Q1 | B2: =C2 -> 35000 | C2: =('Compounding Calculator'!$C$30 * 'Compounding Calculator'!$C$31)/4 -> 35000 | I2: Quartely Interest rate: | J2: ='Compounding Calculator'!C31/4 -> 0.035 | L2: ='Compounding Calculator'!B9 -> 35000
A3: Q2 | B3: =B2 + C3 -> 71225 | C3: =('Compounding Calculator'!$C$30 * 'Compounding Calculator'!$C$31) / 4 + B2 * ('Compounding Calculator'!$C$31 / 4) -> 36225 | I3: Multiplier: | J3: =1+J2 -> 1.035
A4: Q3 | B4: =B3 + C4 -> 108717.88 | C4: =('Compounding Calculator'!$C$30 * 'Compounding Calculator'!$C$31) / 4 + B3 * ('Compounding Calculator'!$C$31 / 4) -> 37492.875
A5: Q4 | B5: =B4 + C5 -> 147523 | C5: =('Compounding Calculator'!$C$30 * 'Compounding Calculator'!$C$31) / 4 + B4 * ('Compounding Calculator'!$C$31 / 4) -> 38805.126 | I5: Investment after 1st Capital Returned: | J5: =#REF!-#REF! -> #REF!
A6: Q5 | B6: =B5 + C6 -> 187686.31 | C6: =('Compounding Calculator'!$C$30 * 'Compounding Calculator'!$C$31) / 4 + B5 * ('Compounding Calculator'!$C$31 / 4) -> 40163.305 | I6: Capital Reinvested 1 | J6: =#REF! -> #REF!
A7: Q6 | B7: =B6 + C7 -> 229255.33 | C7: =('Compounding Calculator'!$C$30 * 'Compounding Calculator'!$C$31) / 4 + B6 * ('Compounding Calculator'!$C$31 / 4) -> 41569.021 | I7: Investment after 2nd Capital Returned: | J7: =#REF!-#REF! -> #REF!
A8: Q7 | B8: =B7 + C8 -> 272279.26 | C8: =('Compounding Calculator'!$C$30 * 'Compounding Calculator'!$C$31) / 4 + B7 * ('Compounding Calculator'!$C$31 / 4) -> 43023.936 | I8: Capital Reinvested 2 | J8: =#REF! -> #REF!
A9: Q8 | B9: =B8 + C9 -> 316809.04 | C9: =('Compounding Calculator'!$C$30 * 'Compounding Calculator'!$C$31) / 4 + B8 * ('Compounding Calculator'!$C$31 / 4) -> 44529.774 | I9: Total value | J9: =SUM('Compounding Calculator'!B9:B28,'Compounding Calculator'!D9:D28) -> 47509537
A10: Q9 | B10: =B9 + C10 -> 362897.35 | C10: =('Compounding Calculator'!$C$30 * 'Compounding Calculator'!$C$31) / 4 + B9 * ('Compounding Calculator'!$C$31 / 4) -> 46088.316
A11: Q10 | B11: =B10 + C11 -> 410598.76 | C11: =('Compounding Calculator'!$C$30 * 'Compounding Calculator'!$C$31) / 4 + B10 * ('Compounding Calculator'!$C$31 / 4) -> 47701.407
A12: Q11 | B12: =B11 + C12 -> 459969.72 | C12: =('Compounding Calculator'!$C$30 * 'Compounding Calculator'!$C$31) / 4 + B11 * ('Compounding Calculator'!$C$31 / 4) -> 49370.957
A13: Q12 | B13: =B12 + C13 -> 511068.66 | C13: =('Compounding Calculator'!$C$30 * 'Compounding Calculator'!$C$31) / 4 + B12 * ('Compounding Calculator'!$C$31 / 4) -> 51098.94
A14: Q13 | B14: =B13 + C14 -> 563956.06 | C14: =('Compounding Calculator'!$C$30 * 'Compounding Calculator'!$C$31) / 4 + B13 * ('Compounding Calculator'!$C$31 / 4) -> 52887.403
A15: Q14 | B15: =B14 + C15 -> 618694.52 | C15: =('Compounding Calculator'!$C$30 * 'Compounding Calculator'!$C$31) / 4 + B14 * ('Compounding Calculator'!$C$31 / 4) -> 54738.462
A16: Q15 | B16: =B15 + C16 -> 675348.83 | C16: =('Compounding Calculator'!$C$30 * 'Compounding Calculator'!$C$31) / 4 + B15 * ('Compounding Calculator'!$C$31 / 4) -> 56654.308
A17: Q16 | B17: =B16 + C17 -> 733986.04 | C17: =('Compounding Calculator'!$C$30 * 'Compounding Calculator'!$C$31) / 4 + B16 * ('Compounding Calculator'!$C$31 / 4) -> 58637.209
A18: Q17 | B18: =B17 + C18 -> 794675.55 | C18: =('Compounding Calculator'!$C$30 * 'Compounding Calculator'!$C$31) / 4 + B17 * ('Compounding Calculator'!$C$31 / 4) -> 60689.511
A19: Q18 | B19: =B18 + C19 -> 857489.2 | C19: =('Compounding Calculator'!$C$30 * 'Compounding Calculator'!$C$31) / 4 + B18 * ('Compounding Calculator'!$C$31 / 4) -> 62813.644
A20: Q19 | B20: =B19 + C20 -> 922501.32 | C20: =('Compounding Calculator'!$C$30 * 'Compounding Calculator'!$C$31) / 4 + B19 * ('Compounding Calculator'!$C$31 / 4) -> 65012.122
A21: Q20 | B21: =B20 + C21 -> 989788.86 | C21: =('Compounding Calculator'!$C$30 * 'Compounding Calculator'!$C$31) / 4 + B20 * ('Compounding Calculator'!$C$31 / 4) -> 67287.546
... A41: Q40 | B41: =B40 + C41 -> 2959259.7 | C41: =('Compounding Calculator'!$C$30 * 'Compounding Calculator'!$C$31) / 4 + B40 * ('Compounding Calculator'!$C$31 / 4) -> 133888.01

Sheet Compounding Calculator
A1: #VALUE! | F1: QUARTERLY COMPOUNDING INVESTMENT CALCULATOR
A8: PROFIT DISRIBUTION
A9: Q1 | B9: =Sheet2!B2 -> 35000 | C9: Q21 | D9: =Sheet2!B22 -> 1059431.5
A10: Q2 | B10: =Sheet2!B3 -> 71225 | C10: Q22 | D10: =Sheet2!B23 -> 1131511.6
A11: Q3 | B11: =Sheet2!B4 -> 108717.88 | C11: Q23 | D11: =Sheet2!B24 -> 1206114.5
A12: Q4 | B12: =Sheet2!B5 -> 147523 | C12: Q24 | D12: =Sheet2!B25 -> 1283328.5
A13: Q5 | B13: =Sheet2!B6 -> 187686.31 | C13: Q25 | D13: =Sheet2!B26 -> 1363245
A14: Q6 | B14: =Sheet2!B7 -> 229255.33 | C14: Q26 | D14: =Sheet2!B27 -> 1445958.6
A15: Q7 | B15: =Sheet2!B8 -> 272279.26 | C15: Q27 | D15: =Sheet2!B28 -> 1531567.1
A16: Q8 | B16: =Sheet2!B9 -> 316809.04 | C16: Q28 | D16: =Sheet2!B29 -> 1620172
A17: Q9 | B17: =Sheet2!B10 -> 362897.35 | C17: Q29 | D17: =Sheet2!B30 -> 1711878
A18: Q10 | B18: =Sheet2!B11 -> 410598.76 | C18: Q30 | D18: =Sheet2!B31 -> 1806793.7
A19: Q11 | B19: =Sheet2!B12 -> 459969.72 | C19: Q31 | D19: =Sheet2!B32 -> 1905031.5
A20: Q12 | B20: =Sheet2!B13 -> 511068.66 | C20: Q32 | D20: =Sheet2!B33 -> 2006707.6
... A28: Q20 | B28: =Sheet2!B21 -> 989788.86 | C28: Q40 | D28: =Sheet2!B41 -> 2959259.7
A30: Investment | C30: 1000000 | F30: Net Profit (10 Years): | I30: =Q30-C30 -> 1959259.7 | N30: Total Accumulated Value (10 Years): | Q30: =D28 -> 2959259.7
A31: Profit (%) | C31: 0.14
A33: Input Investment and Profit Rate Values in the Fields Above
