Workbook

Sheet Front Page
A1: Date: | B1: 45098 | D1: Project description: | G1: Article description: | J1: Weight: | K1: -
A2: Editor: | D2: Program description: | G2: Article No.: | H2: 1816028 | J2: Area: | K2: 462
A3: Version: | B3: Rev 1 | D3: Project lifetime: | E3: 7 | G3: Annual volume: | H3: 150000 | J3: Length: | K3: 66
A4: Customer: | D4: SOP: | E4: 2024 | G4: Permissible variation ∓: | H4: 0.2 | J4: Width: | K4: 7
D5: EOP: | E5: 2031 | G5: Surface: | H5: - | J5: Height: | K5: 425
G6: Layer thickness: | H6: min. Std
H7: max. Std
A9: Location: | B9: - | D9: Plating window (length): | E9: 1500 | G9: Pcs. per row (horizontal): | H9: =ROUNDUP(($E$9-200)/($K$3),0) -> 20
A10: Plating line: | B10: - | D10: Plating window (height): | E10: 1200 | G10: Pcs. per column (vertical): | H10: =ROUNDUP(($E$10-200)/($K$5),0) -> 3
A11: Process: | B11: - | D11: Plating window (width): | E11: 400 | G11: No. of sides (faces): | H11: 2 | J11: Pieces per flight bar: | K11: =H9*H10*H11 -> 120
A13: Annual line capacity (flight bars): | B13: 51840 | D13: Requirement per week: | E13: =H3/50 -> 3000 | G13: (Note: considered 50 weeks per year)
A14: Flight bars annual RFQ article: | B14: =H3/K11 -> 1250 | D14: Requirement per day: | E14: =E13/6 -> 500 | G14: (Note: considered 6 days per week)
A15: Line occupancy for RFQ article: | B15: =B14/B13 -> 0.024112654 | D15: Necessary flight bars: | E15: =+E14/K11/8 -> 0.52083333
E16: =ROUNDUP(E15,0) -> 1 | G16: Flight Bars to be purchased
A18: Price per flight bar: | B18: =E18*K11 -> 41031414 | D18: Price per piece: | E18: =B35 -> 341928.45
G19: Price per dm2: | H19: =E18/100/K2 -> 7.4010486
D20: Annual sales volume: | E20: =E18*H3 -> 5.1289267e+10 | G20: Benchmark [USD per dm2]: | H20: 0.14
D21: Sales volume total project lifetime: | E21: =E20*E3 -> 3.5902487e+11 | G21: Price valuation: | H21: =H19/H20 -> 52.864633
A23: Price for tooling per flight bar: | B23: 5000 | D23: Price for tooling: | E23: =B23*E16 -> 5000
A26: Pieces per Bar | B26: =H9*H10*H11 -> 120
A27: Bars per Hr | B27: 4
A28: Bars Available | B28: =MIN(1,E14/(B26*'Machine Details & Fixed Cost '!J12*'Machine Details & Fixed Cost '!J13)) -> 0.26041667 | C28: =B28/B27 -> 0.065104167
A29: Pieces per Hour | B29: =B26*B27*C28 -> 31.25
A31: Material Rate Hr | B31: ='Variable & Labour Cost'!K30 -> 224.44264
A32: Production Cost Per Piece | B32: =B31/B29 -> 7.1821646
A33: Material Cost per Piece | B33: ='Metal''s Calculator'!D8 -> 207222.18
A34: Material + Production Total | B34: =B32+B33 -> 207229.36
A35: Total Selling Price | B35: =B34*(1+(C35/100)) -> 341928.45 | C35: 65 | D35: Target Profit | E35: =B35-B34 -> 134699.09

Sheet Machine Details & Fixed Cost 
A1: Machine Details & Fixed Cost
A3: Machine Details
A5: Machine Name | B5: Plastic Injection Moulding | G5: Base Currency | H5: Dollars | J5: Date of Entry
A6: Model No. | B6: iArmour350 | G6: Year of Manufacture | H6: 2015 | J6: Site Selection | K6: United States-Illinois-Chicago
A8: Machine Acquisition Cost | G8: Actual Working Hours
A10: M/c Landed Cost | D10: 8000 | G10: Shift Model | J10: 2 Shift -26 Days-8 Hours
A11: Installation Expenses | B11: 5 | C11: % | D11: =((B11/100)*D10) -> 400 | G11: Working Days/Month | J11: =IFERROR(VLOOKUP(J10, 'Dropdown menu'!$D$1:$F$244, 3, FALSE), "") -> 26
A12: Civil Expenses | B12: 5 | C12: % | D12: =((B12/100)*D10) -> 400 | G12: No. of Shifts/Day | J12: =IFERROR(VLOOKUP(J10,'Dropdown menu'!D1:E114, 2, FALSE), "") -> 2
A13: Other Expenses | B13: 3 | C13: % | D13: =((B13/100)*D10) -> 240 | G13: No.of Hours/Shift | J13: =IFERROR(VLOOKUP(J10,'Dropdown menu'!D1:G309, 4, FALSE), "") -> 8
A14: Total Investment | D14: =SUM(D10:D13) -> 9040 | G14: Production Hour per Year | J14: =(J11*J12*J13)*12 -> 4992 | K14: Hr
G15: Operational Efficiency | J15: 80 | K15: %
G16: Actual Working Hours/Year | J16: =(J15/100)*J14 -> 3993.6 | K16: Hr
A19: Fixed Cost
A21: Age of Machine | B21: 15 | C21: Year(s) | G21: Salvage Value -End of Life | H21: 20 | I21: % | J21: =(H21/100) * D14 -> 1808
A22: Interest Rate | B22: 11 | C22: % | G22: Average Annual Investment | J22: =D14-(J24*(INT(B21/2))) -> 5665.0667
A23: Insurance Cost | B23: 0 | C23: % | G23: Interest and Insurance Cost | J23: =(B22/100*(J22)) + ((B23/100)*(J22)) -> 623.15733
A24: Required Gross/Area | B24: 22.58 | C24: m^2 | G24: Calculatory depreciation | J24: =(D14-J21)/B21 -> 482.13333
A25: Space Rent | B25: 25 | C25: (m^2/month) | G25: Space Cost | J25: =(B24*B25*B26*12) -> 7790.1
A26: Foot Print Factor | B26: 1.15 | G26: Total Fixed Cost INR | J26: =(J23+J24+J25) -> 8895.3907
G27: Total Fixed Cost /Hr | J27: =(J26/J16) -> 2.2274115 | K27: /Hr

Sheet Variable & Labour Cost
A1: Variable & Labour Cost
A3: Variable Cost
A5: Total Energy Cost
A7: Connected Power Load | B7: 40.9 | C7: KW | F7: Electricity Cost | G7: 7.6 | H7: /KWH | J7: %Conrtibution | K7: 100
A8: Diesel Consumption | C8: Ltr/Hr | F8: Diesel Cost | G8: 54.22 | H8: /Ltr | J8: %Conrtibution
A9: Any Other Fuel Consumption | C9: Ltr/Hr | F9: Fuel Cost | G9: 32 | H9: /Ltr | J9: %Conrtibution
A10: Performance capacity utilization | B10: 70 | C10: %
J11: Energy Cost | K11: =((B7*(B10/100)*G7*(K7/100))*('Machine Details & Fixed Cost '!J15/100)) + ((B8*(B10/100)*G8)*('Machine Details & Fixed Cost '!J15/100)*(K8/100)) + ((B9*(B10/100)*G9)*('Machine Details & Fixed Cost '!J15/100)*(K9/100)) -> 174.0704 | L11: /Hr
A14: Repair Maintenance & Consumables (Except Tooling)
A16: Repair & Maint. | B16: 2 | C16: %p.a | J16: Repair & Maint. Cost | K16: =(B16/100)*'Machine Details & Fixed Cost '!D14 -> 180.8
A17: Operating Supplies | B17: 1 | C17: %of investment p.a | E17: Or | G17: /Month | J17: Operating Supplies Cost | K17: =IF(AND(B17<>"", F17<>""), "Select p.a. or month", IF(F17<>"", (F17/100)*'Machine Details & Fixed Cost '!D14, IF(B17<>"", (B17/100)*'Machine Details & Fixed Cost '!D14, ""))) -> 90.4
J18: Repair Maint & Consumables Cost | K18: =(K16+K17)/'Machine Details & Fixed Cost '!J16 -> 0.067908654
J19: Total Variable Costs | K19: =K11+K18 -> 174.13831 | L19: /Hr
A22: Labour Cost
A24: Skilled Operators | B24: 1 | C24: Per Shift | F24: Cost/Operator/Month | G24: 10000 | J24: %Utilization | K24: 100
A25: Semi-Skilled Operators | C25: Per Shift | F25: Cost/Operator/Month | J25: %Utilization
A26: Unskilled Operators | C26: Per Shift | F26: Cost/Operator/Month | J26: %Utilization
J28: Labour Cost | K28: =((B24*G24)/('Machine Details & Fixed Cost '!J11 * 'Machine Details & Fixed Cost '!J13)*(K24/100))+((B25*G25) / ('Machine Details & Fixed Cost '!J11 * 'Machine Details & Fixed Cost '!J13)*(K25/100))+((B26*G26) / ('Machine Details & Fixed Cost '!J11 * 'Machine Details & Fixed Cost '!J13)*(K26/100)) -> 48.076923 | L28: /Hr
J30: Machine-Hour Rate | K30: =('Machine Details & Fixed Cost '!J27 + K19+K28) -> 224.44264 | L30: /Hr

Sheet Metal's Calculator
A1: Select Metal(s):
A3: 1st Layer: | B3: Rhodium | C3: Thickness (µm): | D3: 66
C4: Price: | D4: 55
C5: Surface Area (dm2/part): | D5: 46
C6: Coverage (grams/sq. ft.): | D6: =D7/D5 -> 81.906
C7: Grams Deposited (grams): | D7: =(VLOOKUP(B3, 'Dropdown menu'!J1:K464, 2, FALSE)*1000*D3*0.0001*D5) -> 3767.676
C8: 1st Layer Cost: | D8: =D7*D4 -> 207222.18
A10: 2nd Layer: | B10: Rhodium | C10: Thickness (µm): | D10: 33
C11: Price: | D11: 55
C12: Surface Area (dm2/part): | D12: 88
C13: Coverage (grams/sq. ft.): | D13: =D14/D12 -> 40.953
C14: Grams Deposited (grams): | D14: =(VLOOKUP(B10, 'Dropdown menu'!J1:K464, 2, FALSE)*1000*D10*0.0001*D12) -> 3603.864
C15: 2nd Layer Cost: | D15: =D14*D11 -> 198212.52
A17: 3rd Layer: | B17: Gold | C17: Thickness (µm): | D17: 66
C18: Price: | D18: 55 | E18: Total Metal Cost: | H18: =D8+D15+D22 -> 728040.06
C19: Surface Area (dm2/part): | D19: 46
C20: Coverage (grams/sq. ft.): | D20: =D21/D19 -> 127.512
C21: Grams Deposited (grams): | D21: =(VLOOKUP(B17, 'Dropdown menu'!J1:K464, 2, FALSE)*1000*D17*0.0001*D19) -> 5865.552
C22: 3rd Layer Cost: | D22: =D21*D18 -> 322605.36

Sheet Dropdown menu
A1: Machine Names | B1: Model No. | C1: Site Selection | D1: Shift Model | E1: No. of shifts | F1: Days | G1: Hours | J1: Metals | K1: Density (g/cm3)
A2: Plastic Injection Moulding | B2: iArmour350 | C2: India-Punjab-Ludhiana | D2: 2 Shift -26 Days-8 Hours | E2: 2 | F2: 26 | G2: 8 | J2: Candium | K2: 8.65
A3: Another Machine Name Inserted Here | B3: iArmour279 | C3: India-Maharashtra -Mumbai | D3: 2 Shift -14 Days-8 Hours | E3: 2 | F3: 14 | G3: 8 | J3: N/A | K3: 0
A4: Machine Name Inserted | B4: iShield80 | C4: India-West Bengal-Kolkata | D4: 3 Shift -60 Days-4 Hours | E4: 3 | F4: 60 | G4: 4 | J4: Chromium | K4: 7.19
A5: Machine Name Inserted | B5: iShield81 | C5: India-West Bengal-Kolkata | D5: 2 Shift -30 Days-8 Hours | E5: 2 | F5: 30 | G5: 8 | J5: Copper | K5: 8.9
C6: United States-New York-New York City | J6: Gold | K6: 19.32
C7: United States-Florida-Miami | J7: Nickel | K7: 8.9
C8: United States-Illinois-Chicago | J8: Platinum | K8: 21.45
J9: Rhodium | K9: 12.41
J10: Silver | K10: 10.49
J11: Tin | K11: 7.31
J12: Zinc | K12: 7.14
